despot/__init__.py
despot/__main__.py
despot/base.py
despot/batch.py
despot/cli.py
despot/config.py
despot/constants.py
despot/enums.py
despot/exceptions.py
despot/logging.py
despot/metadata.py
despot/models.py
despot/parser.py
despot/utils.py
despot-0.7.0.dist-info/LICENSE
despot-0.7.0.dist-info/METADATA
despot-0.7.0.dist-info/WHEEL
despot-0.7.0.dist-info/entry_points.txt
despot-0.7.0.dist-info/RECORD
