Metadata-Version: 2.3
Name: despot
Version: 0.7.0
Summary: A fast and simple client to free your music from that green streaming service
License: Unlicense
Author: Jan Willhaus
Author-email: mail@janwillhaus.de
Requires-Python: >=3.10,<4.0
Classifier: Development Status :: 4 - Beta
Classifier: Environment :: Console
Classifier: License :: OSI Approved
Classifier: License :: OSI Approved :: The Unlicense (Unlicense)
Classifier: Operating System :: OS Independent
Classifier: Programming Language :: Python :: 3
Classifier: Programming Language :: Python :: 3.10
Classifier: Programming Language :: Python :: 3.11
Classifier: Programming Language :: Python :: 3.12
Classifier: Programming Language :: Python :: 3.13
Classifier: Topic :: Multimedia :: Sound/Audio
Requires-Dist: appdirs (>=1.4.4,<2.0.0)
Requires-Dist: librespot-spotizerr (>=0.3.0,<0.4.0)
Requires-Dist: loguru (>=0.7.2,<0.8.0)
Requires-Dist: mutagen (>=1.47.0,<2.0.0)
Requires-Dist: rich-click (>=1.7.2,<2.0.0)
Project-URL: Bug Reports, https://codeberg.org/janw/despot/issues
Project-URL: Repository, https://codeberg.org/janw/despot.git
